gatorcat/__init__.py
gatorcat-0.0.0.dist-info/METADATA
gatorcat-0.0.0.dist-info/WHEEL
gatorcat-0.0.0.dist-info/top_level.txt
gatorcat-0.0.0.dist-info/RECORD
