Metadata-Version: 2.2
Name: gatorcat
Version: 0.0.0
Summary: Coming soon
Author-email: Jeff Anderson <kj4tmp@gmail.com>
